alitvb-1.0.1.dist-info/DESCRIPTION.rst
alitvb-1.0.1.dist-info/entry_points.txt
alitvb-1.0.1.dist-info/METADATA
alitvb-1.0.1.dist-info/metadata.json
alitvb-1.0.1.dist-info/pbr.json
alitvb-1.0.1.dist-info/RECORD
alitvb-1.0.1.dist-info/top_level.txt
alitvb-1.0.1.dist-info/WHEEL
tvb/cli.py
tvb/command.py
tvb/config.py
tvb/device.py
tvb/excel.py
tvb/info.py
tvb/report.py
tvb/__init__.py
