Metadata-Version: 2.0
Name: alitvb
Version: 1.0.1
Summary: TV Bridge
Home-page: UNKNOWN
Author: Juncheng Chen
Author-email: juncheng.cjc@outlook.com
License: Apache 2.0
Keywords: android adb performence test tv
Platform: UNKNOWN
Classifier: Development Status :: 3 - Alpha
Classifier: Intended Audience :: Developers
Classifier: Topic :: Software Development :: Build Tools
Classifier: License :: OSI Approved :: Apache Software License
Classifier: Programming Language :: Python :: 2
Classifier: Programming Language :: Python :: 2.6
Classifier: Programming Language :: Python :: 2.7
Classifier: Programming Language :: Python :: 3
Classifier: Programming Language :: Python :: 3.5
Requires-Dist: xlsxwriter
